omnata_plugin_devkit/__init__.py
omnata_plugin_devkit/airbyte_wrapper.py
omnata_plugin_devkit/cli/__init__.py
omnata_plugin_devkit/development.ipynb
omnata_plugin_devkit/development_session.py
omnata_plugin_devkit/initialiser.py
omnata_plugin_devkit/jinja_templates/API_LIMITS.sql.jinja
omnata_plugin_devkit/jinja_templates/ASSIGN_OUTBOUND_TARGET_TYPE.sql.jinja
omnata_plugin_devkit/jinja_templates/CONFIGURATION_FORM.sql.jinja
omnata_plugin_devkit/jinja_templates/CONFIGURE_APIS.sql.jinja
omnata_plugin_devkit/jinja_templates/CONNECTION_FORM.sql.jinja
omnata_plugin_devkit/jinja_templates/CONNECTION_TEST.sql.jinja
omnata_plugin_devkit/jinja_templates/CONSTRUCT_FORM_OPTION.sql.jinja
omnata_plugin_devkit/jinja_templates/CREATE_BILLING_EVENTS.sql.jinja
omnata_plugin_devkit/jinja_templates/CREATE_GENERIC_SECRET_OBJECT.sql.jinja
omnata_plugin_devkit/jinja_templates/CREATE_GENERIC_SECRET_OBJECT_FROM_EXISTING.sql.jinja
omnata_plugin_devkit/jinja_templates/CREATE_NETWORK_RULE_OBJECT.sql.jinja
omnata_plugin_devkit/jinja_templates/CREATE_NETWORK_RULE_OBJECT_FROM_EXISTING.sql.jinja
omnata_plugin_devkit/jinja_templates/CREATE_OAUTH_SECRET_OBJECT.sql.jinja
omnata_plugin_devkit/jinja_templates/FETCH_CONNECTIONS.sql.jinja
omnata_plugin_devkit/jinja_templates/FETCH_SYNCS.sql.jinja
omnata_plugin_devkit/jinja_templates/FETCH_SYNC_BRANCHES.sql.jinja
omnata_plugin_devkit/jinja_templates/INBOUND_LIST_STREAMS.sql.jinja
omnata_plugin_devkit/jinja_templates/LIST_STAGES.sql.jinja
omnata_plugin_devkit/jinja_templates/NETWORK_ADDRESSES.sql.jinja
omnata_plugin_devkit/jinja_templates/NGROK_POST_TUNNEL_FIELDS.sql.jinja
omnata_plugin_devkit/jinja_templates/OUTBOUND_RECORD_VALIDATOR.sql.jinja
omnata_plugin_devkit/jinja_templates/PENDING_API_CONFIGURATION.sql.jinja
omnata_plugin_devkit/jinja_templates/POST_INSTALL_ACTIONS.sql.jinja
omnata_plugin_devkit/jinja_templates/RENAME_CONNECTION_METHODS.sql.jinja
omnata_plugin_devkit/jinja_templates/RETRIEVE_NETWORK_RULE_OBJECT.sql.jinja
omnata_plugin_devkit-0.10.26.dist-info/METADATA
omnata_plugin_devkit-0.10.26.dist-info/WHEEL
omnata_plugin_devkit-0.10.26.dist-info/licenses/LICENSE
omnata_plugin_devkit-0.10.26.dist-info/RECORD
