Metadata-Version: 2.4
Name: omnata-plugin-devkit
Version: 0.10.26
Summary: 
License-File: LICENSE
Author: James Weakley
Author-email: james.weakley@omnata.com
Requires-Python: >=3.10,<3.11
Classifier: Programming Language :: Python :: 3
Classifier: Programming Language :: Python :: 3.10
Requires-Dist: behave (>=1.2,<2.0)
Requires-Dist: behave_pandas (>=0.5.0,<0.6.0)
Requires-Dist: jinja2 (>=3,<=3.1.4)
Requires-Dist: numpy (<=1.27.0)
Requires-Dist: omnata-plugin-runtime (>=0.10.20)
Requires-Dist: omnata_cli (>=0.2.3,<0.3.0)
Requires-Dist: pandas (>=2,<=2.1.4)
Requires-Dist: pyparsing (>=3.0)
Requires-Dist: python-slugify (>=8,<9)
Requires-Dist: requirements-parser (==0.5.0)
Requires-Dist: snowflake-connector-python[pandas] (<=3.12.0)
Requires-Dist: tabulate (>=0.9,<0.10)
Requires-Dist: vcrpy (>=4,<5)
